lithops/__init__.py
lithops/config.py
lithops/constants.py
lithops/executors.py
lithops/future.py
lithops/invokers.py
lithops/monitor.py
lithops/plots.py
lithops/retries.py
lithops/utils.py
lithops/version.py
lithops/wait.py
lithops/job/__init__.py
lithops/job/job.py
lithops/job/partitioner.py
lithops/job/serialize.py
lithops/libs/__init__.py
lithops/libs/globber/__init__.py
lithops/libs/globber/globber.py
lithops/libs/imp/__init__.py
lithops/libs/imp/imp.py
lithops/libs/inspect/__init__.py
lithops/libs/inspect/inspect.py
lithops/libs/multyvac/__init__.py
lithops/libs/multyvac/module_dependency.py
lithops/libs/openwhisk/__init__.py
lithops/libs/openwhisk/client.py
lithops/localhost/__init__.py
lithops/localhost/config.py
lithops/localhost/v1/__init__.py
lithops/localhost/v1/localhost.py
lithops/localhost/v1/runner.py
lithops/localhost/v2/__init__.py
lithops/localhost/v2/localhost.py
lithops/localhost/v2/runner.py
lithops/multiprocessing/__init__.py
lithops/multiprocessing/config.py
lithops/multiprocessing/connection.py
lithops/multiprocessing/context.py
lithops/multiprocessing/managers.py
lithops/multiprocessing/pool.py
lithops/multiprocessing/process.py
lithops/multiprocessing/queues.py
lithops/multiprocessing/sharedctypes.py
lithops/multiprocessing/synchronize.py
lithops/multiprocessing/util.py
lithops/scripts/__init__.py
lithops/scripts/cleaner.py
lithops/scripts/cli.py
lithops/serverless/__init__.py
lithops/serverless/serverless.py
lithops/serverless/backends/__init__.py
lithops/serverless/backends/aliyun_fc/__init__.py
lithops/serverless/backends/aliyun_fc/aliyun_fc.py
lithops/serverless/backends/aliyun_fc/config.py
lithops/serverless/backends/aliyun_fc/entry_point.py
lithops/serverless/backends/aws_batch/__init__.py
lithops/serverless/backends/aws_batch/aws_batch.py
lithops/serverless/backends/aws_batch/config.py
lithops/serverless/backends/aws_batch/entry_point.py
lithops/serverless/backends/aws_lambda/__init__.py
lithops-3.6.2.dist-info/LICENSE
lithops-3.6.2.dist-info/METADATA
lithops-3.6.2.dist-info/WHEEL
lithops-3.6.2.dist-info/entry_points.txt
lithops-3.6.2.dist-info/top_level.txt
lithops-3.6.2.dist-info/RECORD
