Metadata-Version: 2.1
Name: lithops
Version: 3.6.2
Summary: Lithops lets you transparently run your Python applications in the Cloud
Home-page: https://github.com/lithops-cloud/lithops
Author: Gil Vernik, Josep Sampe
Author-email: gilv@ibm.com, josep.sampe@gmail.com
License: UNKNOWN
Platform: UNKNOWN
Classifier: Development Status :: 5 - Production/Stable
Classifier: Intended Audience :: Developers
Classifier: Operating System :: OS Independent
Classifier: Natural Language :: English
Classifier: License :: OSI Approved :: Apache Software License
Classifier: Programming Language :: Python :: 3.9
Classifier: Programming Language :: Python :: 3.10
Classifier: Programming Language :: Python :: 3.11
Classifier: Programming Language :: Python :: 3.12
Classifier: Programming Language :: Python :: 3.13
Classifier: Topic :: Software Development :: Libraries :: Python Modules
Classifier: Topic :: Scientific/Engineering
Classifier: Topic :: System :: Distributed Computing
Requires-Python: >=3.6
License-File: LICENSE
Requires-Dist: Click
Requires-Dist: PyYAML
Requires-Dist: cloudpickle
Requires-Dist: paramiko
Requires-Dist: pika
Requires-Dist: ps-mem
Requires-Dist: psutil
Requires-Dist: requests
Requires-Dist: six
Requires-Dist: tabulate
Requires-Dist: tblib
Requires-Dist: tqdm
Provides-Extra: aliyun
Requires-Dist: aliyun-fc2 ; extra == 'aliyun'
Requires-Dist: oss2 ; extra == 'aliyun'
Provides-Extra: all
Requires-Dist: aliyun-fc2 ; extra == 'all'
Requires-Dist: azure-identity ; extra == 'all'
Requires-Dist: azure-mgmt-compute ; extra == 'all'
Requires-Dist: azure-mgmt-network ; extra == 'all'
Requires-Dist: azure-mgmt-resource ; extra == 'all'
Requires-Dist: azure-storage-blob ; extra == 'all'
Requires-Dist: azure-storage-queue ; extra == 'all'
Requires-Dist: boto3 ; extra == 'all'
Requires-Dist: diskcache ; extra == 'all'
Requires-Dist: google-api-python-client ; extra == 'all'
Requires-Dist: google-auth ; extra == 'all'
Requires-Dist: google-cloud-pubsub ; extra == 'all'
Requires-Dist: google-cloud-storage ; extra == 'all'
Requires-Dist: httplib2 ; extra == 'all'
Requires-Dist: ibm-code-engine-sdk ; extra == 'all'
Requires-Dist: ibm-cos-sdk ; extra == 'all'
Requires-Dist: ibm-vpc ; extra == 'all'
Requires-Dist: joblib ; extra == 'all'
Requires-Dist: kubernetes ; extra == 'all'
Requires-Dist: matplotlib ; extra == 'all'
Requires-Dist: numpy ; extra == 'all'
Requires-Dist: oci ; extra == 'all'
Requires-Dist: oss2 ; extra == 'all'
Requires-Dist: pandas ; extra == 'all'
Requires-Dist: pynng ; extra == 'all'
Requires-Dist: pytest ; extra == 'all'
Requires-Dist: redis ; extra == 'all'
Requires-Dist: seaborn ; extra == 'all'
Provides-Extra: aws
Requires-Dist: boto3 ; extra == 'aws'
Provides-Extra: azure
Requires-Dist: azure-identity ; extra == 'azure'
Requires-Dist: azure-mgmt-compute ; extra == 'azure'
Requires-Dist: azure-mgmt-network ; extra == 'azure'
Requires-Dist: azure-mgmt-resource ; extra == 'azure'
Requires-Dist: azure-storage-blob ; extra == 'azure'
Requires-Dist: azure-storage-queue ; extra == 'azure'
Provides-Extra: ceph
Requires-Dist: boto3 ; extra == 'ceph'
Provides-Extra: gcp
Requires-Dist: google-api-python-client ; extra == 'gcp'
Requires-Dist: google-auth ; extra == 'gcp'
Requires-Dist: google-cloud-pubsub ; extra == 'gcp'
Requires-Dist: google-cloud-storage ; extra == 'gcp'
Requires-Dist: httplib2 ; extra == 'gcp'
Provides-Extra: ibm
Requires-Dist: ibm-code-engine-sdk ; extra == 'ibm'
Requires-Dist: ibm-cos-sdk ; extra == 'ibm'
Requires-Dist: ibm-vpc ; extra == 'ibm'
Requires-Dist: kubernetes ; extra == 'ibm'
Provides-Extra: joblib
Requires-Dist: diskcache ; extra == 'joblib'
Requires-Dist: joblib ; extra == 'joblib'
Requires-Dist: numpy ; extra == 'joblib'
Provides-Extra: knative
Requires-Dist: kubernetes ; extra == 'knative'
Provides-Extra: kubernetes
Requires-Dist: kubernetes ; extra == 'kubernetes'
Provides-Extra: minio
Requires-Dist: boto3 ; extra == 'minio'
Provides-Extra: multiprocessing
Requires-Dist: pynng ; extra == 'multiprocessing'
Requires-Dist: redis ; extra == 'multiprocessing'
Provides-Extra: oracle
Requires-Dist: oci ; extra == 'oracle'
Provides-Extra: plotting
Requires-Dist: matplotlib ; extra == 'plotting'
Requires-Dist: numpy ; extra == 'plotting'
Requires-Dist: pandas ; extra == 'plotting'
Requires-Dist: seaborn ; extra == 'plotting'
Provides-Extra: redis
Requires-Dist: redis ; extra == 'redis'
Provides-Extra: tests
Requires-Dist: pytest ; extra == 'tests'
